LICENSE.txt
README.md
__init__.py
metavault.py
setup.cfg
setup.py
MetaVault.egg-info/PKG-INFO
MetaVault.egg-info/SOURCES.txt
MetaVault.egg-info/dependency_links.txt
MetaVault.egg-info/requires.txt
MetaVault.egg-info/top_level.txt