Metadata-Version: 2.1
Name: MetaVault
Version: 0.4.1
Summary: A simple database for storing metadata associated with (media) files.
Download-URL: https://github.com/diontimmer/MetaVault/archive/refs/tags/v_0.4.1.tar.gz
Author: Dion Timmer
Author-email: diontimmer@live.nl
License: MIT
Classifier: Programming Language :: Python :: 3
Classifier: License :: OSI Approved :: MIT License
Classifier: Operating System :: OS Independent
License-File: LICENSE.txt
